itty3.py
itty3-1.1.1.dist-info/AUTHORS
itty3-1.1.1.dist-info/LICENSE
itty3-1.1.1.dist-info/METADATA
itty3-1.1.1.dist-info/WHEEL
itty3-1.1.1.dist-info/top_level.txt
itty3-1.1.1.dist-info/RECORD
