Metadata-Version: 2.1
Name: itty3
Version: 1.1.1
Summary: The itty-bitty Python web framework... **Now Rewritten For Python 3!**
Home-page: http://github.com/toastdriven/itty3/
Author: Daniel Lindsley
Author-email: daniel@toastdriven.com
License: UNKNOWN
Platform: UNKNOWN
Classifier: Development Status :: 5 - Production/Stable
Classifier: Intended Audience :: Developers
Classifier: License :: OSI Approved :: BSD License
Classifier: Operating System :: OS Independent
Classifier: Programming Language :: Python
Classifier: Programming Language :: Python :: 3
